[
    {
        "zh-CN": "装扮",
        "en": "Fashion",
        "ja": "ファッション",
        "zh-TW": "裝扮",
        "kr": "코스튬"
    },
    {
        "zh-CN": "充值",
        "en": "Recharge",
        "ja": "チャージ",
        "zh-TW": "儲值",
        "kr": "충전"
    },
    {
        "zh-CN": "星盘",
        "en": "Star Disc",
        "ja": "星盤",
        "zh-TW": "星盤",
        "kr": "Disc"
    },
    {
        "zh-CN": "礼包",
        "en": "Packs",
        "ja": "パッケージ",
        "zh-TW": "禮包",
        "kr": "패키지"
    },
    {
        "zh-CN": "7日礼包",
        "en": "7-Day Pack",
        "ja": "7日間パック",
        "zh-TW": "7日禮包",
        "kr": "7일 패키지"
    },
    {
        "zh-CN": "皮肤",
        "en": "Skin",
        "ja": "スキン",
        "zh-TW": "造型",
        "kr": "스킨"
    },
    {
        "zh-CN": "头像",
        "en": "Avatar",
        "ja": "アバター",
        "zh-TW": "頭像",
        "kr": "아바타"
    },
    {
        "zh-CN": "名片",
        "en": "Profile Card",
        "ja": "名刺",
        "zh-TW": "名片",
        "kr": "명함"
    },
    {
        "zh-CN": "终结特效",
        "en": "Finisher",
        "ja": "エフェクト",
        "zh-TW": "終結特效",
        "kr": "피니셔"
    },
    {
        "zh-CN": "骰子",
        "en": "Dice",
        "ja": "ダイス",
        "zh-TW": "骰子",
        "kr": "주사위"
    },
    {
        "zh-CN": "卡牌",
        "en": "Card",
        "ja": "カード",
        "zh-TW": "卡牌",
        "kr": "카드"
    },
    {
        "zh-CN": "新手礼包",
        "en": "Beginner Pack",
        "ja": "新規パック",
        "zh-TW": "新手禮包",
        "kr": "신입 추천"
    },
    {
        "zh-CN": "星月票",
        "en": "Monthly Pass",
        "ja": "スター月間パス",
        "zh-TW": "星月票",
        "kr": "월정액"
    },
    {
        "zh-CN": "推荐",
        "en": "推荐",
        "ja": "推荐",
        "zh-TW": "24",
        "kr": "추천"
    },
    {
        "zh-CN": "合作挑战助力",
        "en": "Co-op Challenge Support",
        "ja": "協力チャレンジ助力",
        "zh-TW": "合作挑戰助力",
        "kr": "협동 챌린지 지원"
    },
    {
        "zh-CN": "60",
        "en": "60",
        "ja": "60",
        "zh-TW": "60",
        "kr": "60"
    },
    {
        "zh-CN": "300",
        "en": "300",
        "ja": "300",
        "zh-TW": "300",
        "kr": "300"
    },
    {
        "zh-CN": "680",
        "en": "680",
        "ja": "680",
        "zh-TW": "680",
        "kr": "680"
    },
    {
        "zh-CN": "1280",
        "en": "1280",
        "ja": "1280",
        "zh-TW": "1280",
        "kr": "1280"
    },
    {
        "zh-CN": "3280",
        "en": "3280",
        "ja": "3280",
        "zh-TW": "3280",
        "kr": "3280"
    },
    {
        "zh-CN": "6480",
        "en": "6480",
        "ja": "6480",
        "zh-TW": "6480",
        "kr": "6480"
    },
    {
        "zh-CN": "60星盘",
        "en": "60 Star Disc",
        "ja": "60星盤",
        "zh-TW": "60星盤",
        "kr": "60Disc"
    },
    {
        "zh-CN": "300星盘",
        "en": "300 Star Disc",
        "ja": "300星盤",
        "zh-TW": "300星盤",
        "kr": "300Disc"
    },
    {
        "zh-CN": "680星盘",
        "en": "680 Star Disc",
        "ja": "680星盤",
        "zh-TW": "680星盤",
        "kr": "680Disc"
    },
    {
        "zh-CN": "1280星盘",
        "en": "1280 Star Disc",
        "ja": "1280星盤",
        "zh-TW": "1280星盤",
        "kr": "1280Disc"
    },
    {
        "zh-CN": "3280星盘",
        "en": "3280 Star Disc",
        "ja": "3280星盤",
        "zh-TW": "3280星盤",
        "kr": "3280Disc"
    },
    {
        "zh-CN": "6480星盘",
        "en": "6480 Star Disc",
        "ja": "6480星盤",
        "zh-TW": "6480星盤",
        "kr": "6480Disc"
    },
    {
        "zh-CN": "70",
        "en": "70",
        "ja": "70",
        "zh-TW": "70",
        "kr": "70"
    },
    {
        "zh-CN": "370",
        "en": "370",
        "ja": "370",
        "zh-TW": "370",
        "kr": "370"
    },
    {
        "zh-CN": "640",
        "en": "640",
        "ja": "640",
        "zh-TW": "640",
        "kr": "640"
    },
    {
        "zh-CN": "1500",
        "en": "1500",
        "ja": "1500",
        "zh-TW": "1500",
        "kr": "1500"
    },
    {
        "zh-CN": "2500",
        "en": "2500",
        "ja": "2500",
        "zh-TW": "2500",
        "kr": "2500"
    },
    {
        "zh-CN": "5000",
        "en": "5000",
        "ja": "5000",
        "zh-TW": "5000",
        "kr": "5000"
    },
    {
        "zh-CN": "70星盘",
        "en": "70 Star Disc",
        "ja": "70星盤",
        "zh-TW": "70星盤",
        "kr": "70Disc"
    },
    {
        "zh-CN": "370星盘",
        "en": "370 Star Disc",
        "ja": "370星盤",
        "zh-TW": "370星盤",
        "kr": "370Disc"
    },
    {
        "zh-CN": "640星盘",
        "en": "640 Star Disc",
        "ja": "640星盤",
        "zh-TW": "640星盤",
        "kr": "640Disc"
    },
    {
        "zh-CN": "1500星盘",
        "en": "1500 Star Disc",
        "ja": "1500星盤",
        "zh-TW": "1500星盤",
        "kr": "1500Disc"
    },
    {
        "zh-CN": "2500星盘",
        "en": "2500 Star Disc",
        "ja": "2500星盤",
        "zh-TW": "2500星盤",
        "kr": "2500Disc"
    },
    {
        "zh-CN": "5000星盘",
        "en": "5000 Star Disc",
        "ja": "5000星盤",
        "zh-TW": "5000星盤",
        "kr": "5000Disc"
    },
    {
        "zh-CN": "啦啦队-恋",
        "en": "Cheerleader Ren",
        "ja": "チアリーダー：レン",
        "zh-TW": "啦啦隊-戀",
        "kr": "치어리더 - 렌"
    },
    {
        "zh-CN": "时尚达人-帕露南",
        "en": "Fashion Icon - Parunan",
        "ja": "ファッションプロ-パルナン",
        "zh-TW": "時尚達人-帕露南",
        "kr": "패션의 아이콘 - 파루난"
    },
    {
        "zh-CN": "宝箱怪-璐璐",
        "en": "Mimic-Lulu",
        "ja": "ミミックールル",
        "zh-TW": "寶箱怪-璐璐",
        "kr": "미믹 - 루루"
    },
    {
        "zh-CN": "冰沙快递-米米",
        "en": "Slushie Express- Mimi",
        "ja": "スムージーエキスプレス-ミミ",
        "zh-TW": "冰沙快遞-米米",
        "kr": "슬러시 익스프레스 - 미미"
    },
    {
        "zh-CN": "战斗女仆-枫",
        "en": "Maid-Warrior: Fen",
        "ja": "バトルメイド-ヒメ",
        "zh-TW": "戰鬥女僕-楓",
        "kr": "전투 메이드 - 펜"
    },
    {
        "zh-CN": "战斗女仆-美咲",
        "en": "Maid-Warrior: Misaki",
        "ja": "バトルメイド-ミサキ",
        "zh-TW": "戰鬥女僕-美咲",
        "kr": "전투 메이드 - 미사키"
    },
    {
        "zh-CN": "忍者为何？-小町",
        "en": "Why the Ninja? - Komachi",
        "ja": "ニンジャナンデ！？-コマチ",
        "zh-TW": "忍者爲何？-小町",
        "kr": "닌자는 왜?! - 코마치"
    },
    {
        "zh-CN": "护卫队长-帕帕拉",
        "en": "Guard Captain - Papala",
        "ja": "護衛隊長-パパラ",
        "zh-TW": "護衛隊長-帕帕拉",
        "kr": "호위대장-파파라"
    },
    {
        "zh-CN": "冒失少女-阿兰娜",
        "en": "Clumsy Girl - Alana",
        "ja": "ドジっ子-アランナ",
        "zh-TW": "冒失少女-阿蘭娜",
        "kr": "덜렁이 - 알리나"
    },
    {
        "zh-CN": "海滨救援-梅加斯",
        "en": "Seaside Rescue - Megas",
        "ja": "マリンレスキュー-メガス",
        "zh-TW": "海濱救援-梅加斯",
        "kr": "라이프가드 - 메가스"
    },
    {
        "zh-CN": "海湾假日-凛",
        "en": "Harbour Holiday - Rin",
        "ja": "浜辺のバカンス-リン",
        "zh-TW": "海灣假日-凜",
        "kr": "해변의 바캉스 - 린"
    },
    {
        "zh-CN": "冲浪海岸-茉莉",
        "en": "Coastal Surfer - Jasmine",
        "ja": "エンドレスサーフィン-ジャスミン",
        "zh-TW": "沖浪海岸-茉莉",
        "kr": "해변의 서퍼 - 쟈스민"
    },
    {
        "zh-CN": "7日超值礼包",
        "en": "7-Day Value Pack",
        "ja": "7日間お得パック",
        "zh-TW": "7日超值禮包",
        "kr": "7일 특별 패키지"
    },
    {
        "zh-CN": "合作挑战 7日助力礼包",
        "en": "Co-op Challenge 7-Day Support Pack",
        "ja": "協力チャレンジ七日間助力パック",
        "zh-TW": "合作挑戰 7日助力禮包",
        "kr": "협동 챌린지 7일 지원 패키지"
    },
    {
        "zh-CN": "通行证",
        "en": "Season Pass",
        "ja": "シーズンパス",
        "zh-TW": "通行證",
        "kr": "시즌 패스"
    },
    {
        "zh-CN": "通行证-升级版",
        "en": "Season Pass Premier",
        "ja": "プレミアムパス",
        "zh-TW": "通行證-升級版",
        "kr": "시즌 패스 Premium"
    },
    {
        "zh-CN": "通行证-升级",
        "en": "Season Pass - Upgrade",
        "ja": "パスアップグレード",
        "zh-TW": "通行證-升級",
        "kr": "시즌 패스 Upgrade"
    },
    {
        "zh-CN": "联动角色 组合包",
        "en": "Collaboration Character Bundle",
        "ja": "コラボキャラパック",
        "zh-TW": "聯動角色 組合包",
        "kr": "콜라보 캐릭터 번들"
    },
    {
        "zh-CN": "超绝天使-超天酱 组合包",
        "en": "OMGKawaiiAngel - KAngel Pack",
        "ja": "超天ちゃんパック",
        "zh-TW": "超絕天使-超天醬 組合包",
        "kr": "OMGKawaiiAngel 패키지"
    },
    {
        "zh-CN": "主播女孩-糖糖 组合包",
        "en": "NeedyGirl - Ame Pack",
        "ja": "あめちゃんパック",
        "zh-TW": "主播女孩-糖糖 組合包",
        "kr": "Ame 패키지"
    },
    {
        "zh-CN": "魔女兵器-阿兰娜",
        "en": "Witch's Weapon - Alana",
        "ja": "魔女兵器-アランナ",
        "zh-TW": "魔女兵器-阿蘭娜",
        "kr": "마녀병기 - 알라나"
    },
    {
        "zh-CN": "魔女兵器-美咲",
        "en": "Witch's Weapon - Msaki",
        "ja": "魔女兵器-ミサキ",
        "zh-TW": "魔女兵器-美咲",
        "kr": "마녀병기-미사키"
    },
    {
        "zh-CN": "魔女兵器皮肤组合",
        "en": "Witch’s Weapon Skin Pack",
        "ja": "魔女兵器スキンパック",
        "zh-TW": "魔女兵器皮膚組合",
        "kr": "마녀병기 스킨 패키지"
    }
]